quark_runtime.py
datawire_quark_core-0.4.2.dist-info/DESCRIPTION.rst
datawire_quark_core-0.4.2.dist-info/METADATA
datawire_quark_core-0.4.2.dist-info/RECORD
datawire_quark_core-0.4.2.dist-info/WHEEL
datawire_quark_core-0.4.2.dist-info/metadata.json
datawire_quark_core-0.4.2.dist-info/top_level.txt
