Metadata-Version: 2.0
Name: datawire-quark-core
Version: 0.4.2
Summary: Core runtime for Python code generated by Quark
Home-page: http://datawire.github.io/quark
Author: datawire.io
Author-email: hello@datawire.io
License: Apache License, Version 2.0
Platform: UNKNOWN
